configuration_settings/__init__.py
configuration_settings/config.py
configuration_settings/py.typed
configuration_settings-1.0.0.dist-info/LICENSE
configuration_settings-1.0.0.dist-info/METADATA
configuration_settings-1.0.0.dist-info/WHEEL
configuration_settings-1.0.0.dist-info/top_level.txt
configuration_settings-1.0.0.dist-info/RECORD
