Metadata-Version: 2.1
Name: configuration-settings
Version: 1.0.0
Summary: General purpose config file parser
Author-email: Peter Linss <peter@linss.com>
License: GNU Lesser General Public License v3
Project-URL: homepage, https://gitlab.linss.com/open-source/python/configuration-settings
Keywords: config
Classifier: Intended Audience :: Developers
Classifier: License :: OSI Approved :: GNU Lesser General Public License v3 or later (LGPLv3+)
Classifier: Programming Language :: Python
Classifier: Programming Language :: Python :: 3
Classifier: Programming Language :: Python :: 3.9
Classifier: Programming Language :: Python :: 3.10
Classifier: Programming Language :: Python :: 3.11
Classifier: Topic :: Software Development :: Libraries :: Python Modules
Requires-Python: >=3.9
Provides-Extra: dev
License-File: LICENSE
